odoo/addons/account_invoice_block_payment/README.md
odoo/addons/account_invoice_block_payment/README.rst
odoo/addons/account_invoice_block_payment/__init__.py
odoo/addons/account_invoice_block_payment/__manifest__.py
odoo/addons/account_invoice_block_payment/i18n/account_invoice_block_payment.pot
odoo/addons/account_invoice_block_payment/i18n/de.po
odoo/addons/account_invoice_block_payment/i18n/fr.po
odoo/addons/account_invoice_block_payment/i18n/it.po
odoo/addons/account_invoice_block_payment/models/__init__.py
odoo/addons/account_invoice_block_payment/models/account_move.py
odoo/addons/account_invoice_block_payment/readme/CONTRIBUTORS.rst
odoo/addons/account_invoice_block_payment/readme/DESCRIPTION.rst
odoo/addons/account_invoice_block_payment/readme/USAGE.rst
odoo/addons/account_invoice_block_payment/static/description/icon.png
odoo/addons/account_invoice_block_payment/static/description/index.html
odoo/addons/account_invoice_block_payment/tests/__init__.py
odoo/addons/account_invoice_block_payment/tests/test_account_block_payment.py
odoo/addons/account_invoice_block_payment/views/account_move.xml
odoo14_addon_account_invoice_block_payment-14.0.1.0.1.dev5.dist-info/METADATA
odoo14_addon_account_invoice_block_payment-14.0.1.0.1.dev5.dist-info/WHEEL
odoo14_addon_account_invoice_block_payment-14.0.1.0.1.dev5.dist-info/top_level.txt
odoo14_addon_account_invoice_block_payment-14.0.1.0.1.dev5.dist-info/RECORD
